record3d.cpython-38-x86_64-linux-gnu.so
record3d-1.4.1.dist-info/LICENSE
record3d-1.4.1.dist-info/METADATA
record3d-1.4.1.dist-info/WHEEL
record3d-1.4.1.dist-info/top_level.txt
record3d-1.4.1.dist-info/RECORD
