Metadata-Version: 2.1
Name: record3d
Version: 1.4.1
Summary: Accompanying library for the Record3D iOS app (https://record3d.app/). Allows you to receive RGBD stream from iOS devices with TrueDepth and/or LiDAR camera(s).
Home-page: https://github.com/marek-simonik/record3d
Author: Marek Simonik
Author-email: admin@record3d.app
License: lgpl-2.1
Keywords: record3d,iOS,TrueDepth,streaming,pointcloud,point,cloud
License-File: LICENSE
Requires-Dist: numpy
